{"sections":{"main":{"type":"page","settings":{"show-title":true,"background-color":"none","light-text":false,"container-width":4,"spacing-above":true,"spacing-below":true}},"1649771902fbbd66ec":{"type":"apps","blocks":{"2be9774b-c685-445f-b37c-be21ff5d709e":{"type":"shopify:\/\/apps\/loox-product-reviews-photos\/blocks\/loox-agg-section\/5c3b337f-fd14-4df5-b1d6-80ec13e6e28e","settings":{"only_photos":false,"hide_thumbnails":false,"product_handle":"","aggregated":true,"data-limit":20,"maxwidth":1080}}},"block_order":["2be9774b-c685-445f-b37c-be21ff5d709e"],"settings":{"background-color":"none","light-text":false,"container-width":4,"spacing-above":true,"spacing-below":true}}},"order":["main","1649771902fbbd66ec"]}